[[{"__type__":"cc.SceneAsset","_name":"PhysicsTest","scene":{"__id__":1},"asyncLoadAssets":null},{"__type__":"cc.Scene","_name":"New Node","_children":[{"__id__":2},{"__id__":4},{"__id__":5},{"__id__":6},{"__id__":7},{"__id__":8},{"__id__":9}],"_anchorPoint":{"__type__":"cc.Vec2"},"autoReleaseAssets":false},{"__type__":"cc.Node","_name":"Canvas","_parent":{"__id__":1},"_children":[{"__id__":3}],"_components":[{"__type__":"cc.Canvas","node":{"__id__":2}}],"_contentSize":{"__type__":"cc.Size","width":960,"height":640},"_position":{"__type__":"cc.Vec3","x":480,"y":320},"_id":"91mFqEGrhBpKEdX58t1cqy"},{"__type__":"cc.Node","_name":"Main Camera","_parent":{"__id__":2},"_level":1,"_components":[{"__type__":"cc.Camera","node":{"__id__":3},"_clearFlags":7,"_depth":-1,"_ortho":false}]},{"__type__":"cc.Node","_name":"sprite_splash","_parent":{"__id__":1},"_level":1,"_components":[{"__type__":"cc.Sprite","node":{"__id__":4},"_materials":[{"__uuid__":"ecpdLyjvZBwrvm+cedCcQy"}],"_spriteFrame":{"__uuid__":"1aMvx28L1PZpgPVpKcDKCz"},"_sizeMode":0},{"__type__":"cc.RigidBody","node":{"__id__":4},"_gravityScale":2,"_fixedRotation":true,"enabledContactListener":true},{"__type__":"cc.PhysicsCircleCollider","node":{"__id__":4},"_radius":10},{"__type__":"527c01rTJVPI40Q7YRwMQ8F","node":{"__id__":4}},{"__type__":"1c2fd91AZFLmJ3EAXgTqHgV","node":{"__id__":4}}],"_contentSize":{"__type__":"cc.Size","width":25,"height":25},"_position":{"__type__":"cc.Vec3","x":238.38,"y":375.691},"_id":"88Gm7xtGROvIFehH2CPpOt"},{"__type__":"cc.Node","_name":"sprite","_parent":{"__id__":1},"_level":1,"_components":[{"__type__":"cc.Sprite","node":{"__id__":5},"_materials":[{"__uuid__":"ecpdLyjvZBwrvm+cedCcQy"}],"_spriteFrame":{"__uuid__":"8c20Sso/ZEn7NUfNSM+EBh"}},{"__type__":"cc.RigidBody","node":{"__id__":5},"_type":0},{"__type__":"cc.PhysicsBoxCollider","node":{"__id__":5},"_size":{"__type__":"cc.Size","width":40,"height":36}}],"_contentSize":{"__type__":"cc.Size","width":40,"height":36},"_position":{"__type__":"cc.Vec3","x":479.132,"y":36.635},"_scale":{"__type__":"cc.Vec3","x":35.246,"y":1.488,"z":1},"_id":"a0TUpPuFRHTKZGgxadm1vR"},{"__type__":"cc.Node","_name":"sprite copy","_parent":{"__id__":1},"_level":1,"_components":[{"__type__":"cc.Sprite","node":{"__id__":6},"_materials":[{"__uuid__":"ecpdLyjvZBwrvm+cedCcQy"}],"_spriteFrame":{"__uuid__":"8c20Sso/ZEn7NUfNSM+EBh"}},{"__type__":"cc.RigidBody","node":{"__id__":6},"_type":0},{"__type__":"cc.PhysicsBoxCollider","node":{"__id__":6},"_size":{"__type__":"cc.Size","width":40,"height":36}}],"_contentSize":{"__type__":"cc.Size","width":40,"height":36},"_position":{"__type__":"cc.Vec3","x":26.809,"y":334.253},"_scale":{"__type__":"cc.Vec3","x":35.246,"y":1.488,"z":1},"_eulerAngles":{"__type__":"cc.Vec3","z":90},"_id":"b3cACNclJOvoD7SEn2pp2Z"},{"__type__":"cc.Node","_name":"sprite_splash","_parent":{"__id__":1},"_level":1,"_components":[{"__type__":"cc.Sprite","node":{"__id__":7},"_materials":[{"__uuid__":"ecpdLyjvZBwrvm+cedCcQy"}],"_spriteFrame":{"__uuid__":"a2MjXRFdtLlYQ5ouAFv/+R"},"_sizeMode":0},{"__type__":"cc.RigidBody","node":{"__id__":7}},{"__type__":"cc.PhysicsBoxCollider","node":{"__id__":7}}],"_contentSize":{"__type__":"cc.Size","width":100,"height":100},"_position":{"__type__":"cc.Vec3","x":641.778,"y":140.453},"_scale":{"__type__":"cc.Vec3","x":0.456,"y":1,"z":1},"_id":"b7tovc/ERK1YuVtYiuvoXy"},{"__type__":"cc.Node","_name":"sprite_splash copy","_parent":{"__id__":1},"_level":1,"_components":[{"__type__":"cc.Sprite","node":{"__id__":8},"_materials":[{"__uuid__":"ecpdLyjvZBwrvm+cedCcQy"}],"_spriteFrame":{"__uuid__":"a2MjXRFdtLlYQ5ouAFv/+R"},"_sizeMode":0},{"__type__":"cc.RigidBody","node":{"__id__":8}},{"__type__":"cc.PhysicsBoxCollider","node":{"__id__":8}}],"_contentSize":{"__type__":"cc.Size","width":100,"height":100},"_position":{"__type__":"cc.Vec3","x":829.675,"y":196.127},"_scale":{"__type__":"cc.Vec3","x":0.456,"y":2.208,"z":1},"_eulerAngles":{"__type__":"cc.Vec3","z":90},"_id":"43za7ps9FNb62nR7z5Bb8G"},{"__type__":"cc.Node","_name":"Manager","_parent":{"__id__":1},"_level":1,"_components":[{"__type__":"c191dju3ERH0oA8+8hpE/7n","node":{"__id__":9}},{"__type__":"127e8VSZjdCH5q3DwbQdtjD","node":{"__id__":9}}],"_id":"5e+mN7YPNDR6GQxgY4lHII"}],{"__type__":"cc.SpriteFrame","content":{"name":"default_radio_button_on","texture":"9dYAAftfRHJqYpJlnj3tC4","rect":[1,1,30,30],"offset":[0,0],"originalSize":[32,32],"capInsets":[0,0,0,0]}},{"__type__":"cc.SpriteFrame","content":{"name":"default_sprite","texture":"6eBWFz0oVHPLIGQKf/9Thu","rect":[0,2,40,36],"offset":[0,0],"originalSize":[40,40],"capInsets":[0,0,0,0]}},{"__type__":"cc.SpriteFrame","content":{"name":"default_sprite_splash","texture":"02delMVqdBD70a/HSD99FK","rect":[0,0,2,2],"offset":[0,0],"originalSize":[2,2],"capInsets":[0,0,0,0]}}]